abx_plugin_singlefile/__init__.py
abx_plugin_singlefile/actors.py
abx_plugin_singlefile/binaries.py
abx_plugin_singlefile/config.py
abx_plugin_singlefile/extractors.py
abx_plugin_singlefile/models.py
abx_plugin_singlefile/singlefile.py
abx_plugin_singlefile-2024.10.28.dist-info/METADATA
abx_plugin_singlefile-2024.10.28.dist-info/WHEEL
abx_plugin_singlefile-2024.10.28.dist-info/entry_points.txt
abx_plugin_singlefile-2024.10.28.dist-info/RECORD
